cde/BaseConditionalDensity.py
cde/__init__.py
cde/density_estimator/BaseDensityEstimator.py
cde/density_estimator/BaseNNEstimator.py
cde/density_estimator/BaseNNMixtureEstimator.py
cde/density_estimator/CKDE.py
cde/density_estimator/KMN.py
cde/density_estimator/LSCDE.py
cde/density_estimator/MDN.py
cde/density_estimator/NF.py
cde/density_estimator/NKDE.py
cde/density_estimator/__init__.py
cde/density_estimator/torch_base.py
cde/density_estimator/normalizing_flows/AffineFlow.py
cde/density_estimator/normalizing_flows/BaseNormalizingFlow.py
cde/density_estimator/normalizing_flows/IdentityFlow.py
cde/density_estimator/normalizing_flows/PlanarFlow.py
cde/density_estimator/normalizing_flows/RadialFlow.py
cde/density_estimator/normalizing_flows/__init__.py
cde/density_simulation/ArmaJump.py
cde/density_simulation/BaseConditionalDensitySimulation.py
cde/density_simulation/EconDensity.py
cde/density_simulation/GMM.py
cde/density_simulation/JumpDiffusionModel.py
cde/density_simulation/LinearGaussian.py
cde/density_simulation/LinearStudentT.py
cde/density_simulation/SkewNormal.py
cde/density_simulation/__init__.py
cde/density_simulation/toy_densities.py
cde/evaluation/__init__.py
cde/evaluation/empirical_eval/__init__.py
cde/evaluation/empirical_eval/benchmark_empirical.py
cde/evaluation/empirical_eval/benchmark_empirical_kde.py
cde/evaluation/empirical_eval/datasets.py
cde/evaluation/empirical_eval/experiment_util.py
cde/evaluation/empirical_eval/regularization_empirical.py
cde/evaluation/eurostoxx_eval/__init__.py
cde/evaluation/eurostoxx_eval/empirical_benchmark.py
cde/evaluation/eurostoxx_eval/feature_selection.py
cde/evaluation/eurostoxx_eval/fit_density.py
cde/evaluation/eurostoxx_eval/load_dataset.py
cde/evaluation/eurostoxx_eval/moments_time_series.py
cde/evaluation/eurostoxx_eval/noise_reg_plots.py
cde/evaluation/eurostoxx_eval/underest_of_variance.py
cde/evaluation/simulation_eval/__init__.py
cde/evaluation/simulation_eval/base_experiment.py
cde-1.0.1.dist-info/licenses/LICENSE
cde-1.0.1.dist-info/METADATA
cde-1.0.1.dist-info/WHEEL
cde-1.0.1.dist-info/top_level.txt
cde-1.0.1.dist-info/RECORD
