Metadata-Version: 2.4
Name: cde
Version: 1.0.1
Summary: Framework for conditional density estimation
Home-page: https://github.com/freelunchtheorem/Conditional_Density_Estimation
Author: Jonas Rothfuss, Fabio Ferreira
Author-email: jonas.rothfuss@gmx.de, fabioferreira@mailbox.org
License: MIT
License-File: LICENSE
Requires-Dist: numpy
Requires-Dist: pandas
Requires-Dist: matplotlib
Requires-Dist: scipy
Requires-Dist: seaborn
Requires-Dist: pytest
Requires-Dist: scikit_learn
Requires-Dist: statsmodels
Requires-Dist: wandb
Dynamic: author
Dynamic: author-email
Dynamic: description
Dynamic: description-content-type
Dynamic: home-page
Dynamic: license
Dynamic: license-file
Dynamic: requires-dist
Dynamic: summary
